fabric_webbuilders/__init__.py
fabric_webbuilders/base.py
fabric_webbuilders/bootstrap.py
fabric_webbuilders/cssmin.py
fabric_webbuilders/jquery.py
fabric_webbuilders/jsmin.py
fabric_webbuilders-0.3.dist-info/DESCRIPTION.rst
fabric_webbuilders-0.3.dist-info/METADATA
fabric_webbuilders-0.3.dist-info/RECORD
fabric_webbuilders-0.3.dist-info/WHEEL
fabric_webbuilders-0.3.dist-info/metadata.json
fabric_webbuilders-0.3.dist-info/top_level.txt
