Metadata-Version: 2.0
Name: fabric-webbuilders
Version: 0.3
Summary: Build customized and up-to-date versions of HTML/JS/CSS libraries and minify them.
Home-page: https://github.com/mathiasertl/fabric-webbuilders
Author: Mathias Ertl
Author-email: mati@er.tl
License: GNU General Public License (GPL) v3
Download-URL: https://github.com/mathiasertl/fabric-webbuilders
Platform: any
Classifier: Development Status :: 6 - Mature
Classifier: Environment :: Other Environment
Classifier: Environment :: Web Environment
Classifier: Intended Audience :: Developers
Classifier: Intended Audience :: System Administrators
Classifier: License :: OSI Approved :: GNU General Public License v3 or later (GPLv3+)
Classifier: Operating System :: OS Independent
Classifier: Programming Language :: Python :: 2
Classifier: Programming Language :: Python :: 2.7
Classifier: Programming Language :: Python :: 3
Classifier: Programming Language :: Python :: 3.2
Classifier: Programming Language :: Python :: 3.3
Classifier: Programming Language :: Python :: 3.4
Classifier: Programming Language :: Python :: 3.5
Classifier: Programming Language :: Python
Classifier: Topic :: Internet :: WWW/HTTP
Classifier: Topic :: Software Development :: Libraries :: Python Modules
Requires-Dist: GitPython (>=1.0.2)
